{
    "scenes": [
        {
            "scene_id": "start",
            "text": "Лёха сидит перед монитором, опустив руки после очередного поражения. Его аккаунт пылает от лузстрика длиной в 30 матчей. Мысли мелькают одна за другой — удалить игру? Но тут появляется новость о новом патче. Антимаг теперь настоящая скрытая мета. Лёха решает рискнуть. Новая жизнь начинается здесь.",
            "choices": [
                {
                    "text": "Посмотреть гайд на YouTube",
                    "next_scene": "youtube_guide"
                },
                {
                    "text": "Купить книгу про стратегию игры",
                    "next_scene": "book_strategy"
                },
                {
                    "text": "Обратиться к опытному другу-простаку",
                    "next_scene": "friend_help"
                }
            ]
        },
        {
            "scene_id": "youtube_guide",
            "text": "На канале гуру стримера раскрываются секреты механики Антимага. Ты узнаешь всё о билде, нюансах крипинга и фарминга, стратегии ведения боя. После просмотра ты чувствуешь себя готовым идти в бой... почти.",
            "choices": [
                {
                    "text": "Попробовать сразу же в игре",
                    "next_scene": "try_game"
                },
                {
                    "text": "Повторно посмотреть руководство",
                    "next_scene": "rewatch_guide"
                }
            ]
        },
        {
            "scene_id": "book_strategy",
            "text": "Книга написана профессиональным игроком и аналитиком. Она погружает тебя в тактику борьбы против магов, тонкости фарма и преимущества быстрого прокачивания. Перед тобой открываются двери мастерства. Что дальше?",
            "choices": [
                {
                    "text": "Практиковаться в одиночной тренировке",
                    "next_scene": "training_solo"
                },
                {
                    "text": "Найти друга и потренироваться вместе",
                    "next_scene": "train_with_friend"
                }
            ]
        },
        {
            "scene_id": "friend_help",
            "text": "Твой друг Макс объясняет тебе основы игры за Антимага, делится опытом и даёт советы по эффективному использованию способностей героя. Вместе вы создаёте план действий. Настало время применить полученные знания!",
            "choices": [
                {
                    "text": "Создать группу и сыграть матч",
                    "next_scene": "group_match"
                },
                {
                    "text": "Играть соло в режиме practice",
                    "next_scene": "solo_practice"
                }
            ]
        },
        {
            "scene_id": "try_game",
            "text": "Ты входишь в лобби матча и выбираешь Антимага. Первые минуты напряжённые, но постепенно понимаешь механику и применяешь изученные техники. Матч заканчивается победой. Это было начало конца твоего лузстрика.",
            "choices": [
                {
                    "text": "Продолжить серию побед",
                    "next_scene": "win_streak"
                }
            ]
        },
        {
            "scene_id": "rewatch_guide",
            "text": "Ещё раз пересмотрев ролик, ты лучше усваиваешь ключевые моменты и начинаешь понимать тонкие нюансы игры. Теперь ты готов попробовать снова, чувствуя уверенность в себе.",
            "choices": [
                {
                    "text": "Вернуться в стартовую сцену",
                    "next_scene": "start"
                }
            ]
        },
        {
            "scene_id": "training_solo",
            "text": "Одиночная тренировка позволяет отработать начальные стадии игры и оптимизировать процесс фарма. Теперь ты уверенно чувствуешь себя в начальной фазе, осталось проверить себя в настоящем матче.",
            "choices": [
                {
                    "text": "Зайти в рейтинговый матч",
                    "next_scene": "ranked_match"
                }
            ]
        },
        {
            "scene_id": "train_with_friend",
            "text": "Тренировки с другом помогают развивать командную работу и улучшать понимание ролей в команде. Ваш совместный успех вдохновляет вас обоих двигаться вперёд и достигать новых высот.",
            "choices": [
                {
                    "text": "Организовать групповое событие",
                    "next_scene": "organize_event"
                }
            ]
        },
        {
            "scene_id": "group_match",
            "text": "Играя в группе с друзьями, ты быстро адаптируешься к роли поддержки и ключевой фигуры команды. Вы выигрываете несколько матчей подряд, улучшая ваши рейтинги и репутацию.",
            "choices": [
                {
                    "text": "Устроить турнир среди друзей",
                    "next_scene": "friends_tournament"
                }
            ]
        },
        {
            "scene_id": "solo_practice",
            "text": "Одинокая практика помогает освоить технику и разобраться в сложных ситуациях. Постепенно ты становишься увереннее и ощущаешь готовность выйти в настоящий рейтинговый матч.",
            "choices": [
                {
                    "text": "Идти в рейтинговые матчи",
                    "next_scene": "enter_ranked"
                }
            ]
        },
        {
            "scene_id": "win_streak",
            "text": "Серия побед приносит удовольствие и поднимает твой моральный дух. Игра кажется простой, каждый матч идёт легче предыдущего. Всё-таки решение начать играть на Антимаге оказалось верным.",
            "choices": []
        },
        {
            "scene_id": "ranked_match",
            "text": "Первый рейтинговый матч оказался непростым испытанием. Однако, благодаря полученным навыкам, ты справляешься успешно. Рейтинг растёт, настроение улучшается, игра вновь радует тебя.",
            "choices": []
        },
        {
            "scene_id": "organize_event",
            "text": "Турнир среди друзей проходит весело и увлекательно. Каждый участник получает полезный опыт, а атмосфера соревнования заряжает позитивом. Победителем турнира становится твоя команда, а личный уровень поднимается ещё выше.",
            "choices": []
        },
        {
            "scene_id": "friends_tournament",
            "text": "Соревнование стало настоящим праздником. Атмосфера дружелюбности и азарта царит вокруг. Полученный опыт и победа приносят удовлетворение и радость каждому участнику. Этот день останется незабываемым.",
            "choices": []
        },
        {
            "scene_id": "enter_ranked",
            "text": "Теперь ты смело заходишь в рейтинговые матчи, используя накопленные знания и умения. Каждое поражение воспринимается как урок, каждая победа — как достижение. Мораль поднята, прогресс очевиден.",
            "choices": []
        }
    ]
}